peep.py
peep-3.1.2.dist-info/DESCRIPTION.rst
peep-3.1.2.dist-info/METADATA
peep-3.1.2.dist-info/RECORD
peep-3.1.2.dist-info/WHEEL
peep-3.1.2.dist-info/entry_points.txt
peep-3.1.2.dist-info/metadata.json
peep-3.1.2.dist-info/top_level.txt
