Metadata-Version: 2.0
Name: peep
Version: 3.1.2
Summary: A "pip install" that is cryptographically guaranteed repeatable
Home-page: https://github.com/erikrose/peep
Author: Erik Rose
Author-email: grinch@grinchcentral.com
License: MIT
Keywords: pip,secure,repeatable,deploy,deployment,hash,install,installer
Platform: UNKNOWN
Classifier: Intended Audience :: Developers
Classifier: Intended Audience :: System Administrators
Classifier: License :: OSI Approved :: MIT License
Classifier: Programming Language :: Python :: 2
Classifier: Programming Language :: Python :: 2.6
Classifier: Programming Language :: Python :: 2.7
Classifier: Programming Language :: Python :: 3
Classifier: Programming Language :: Python :: 3.3
Classifier: Programming Language :: Python :: 3.4
Classifier: Programming Language :: Python :: 3.5
Classifier: Topic :: Software Development :: Build Tools
Classifier: Topic :: System :: Installation/Setup
Classifier: Topic :: System :: Systems Administration
